alibabacloud_cas20200630/__init__.py
alibabacloud_cas20200630/client.py
alibabacloud_cas20200630/models/__init__.py
alibabacloud_cas20200630/models/_assign_certificate_count_request.py
alibabacloud_cas20200630/models/_assign_certificate_count_response.py
alibabacloud_cas20200630/models/_assign_certificate_count_response_body.py
alibabacloud_cas20200630/models/_create_client_certificate_request.py
alibabacloud_cas20200630/models/_create_client_certificate_response.py
alibabacloud_cas20200630/models/_create_client_certificate_response_body.py
alibabacloud_cas20200630/models/_create_client_certificate_with_csr_request.py
alibabacloud_cas20200630/models/_create_client_certificate_with_csr_response.py
alibabacloud_cas20200630/models/_create_client_certificate_with_csr_response_body.py
alibabacloud_cas20200630/models/_create_custom_certificate_request.py
alibabacloud_cas20200630/models/_create_custom_certificate_response.py
alibabacloud_cas20200630/models/_create_custom_certificate_response_body.py
alibabacloud_cas20200630/models/_create_external_cacertificate_request.py
alibabacloud_cas20200630/models/_create_external_cacertificate_response.py
alibabacloud_cas20200630/models/_create_external_cacertificate_response_body.py
alibabacloud_cas20200630/models/_create_external_cacertificate_shrink_request.py
alibabacloud_cas20200630/models/_create_revoke_client_certificate_request.py
alibabacloud_cas20200630/models/_create_revoke_client_certificate_response.py
alibabacloud_cas20200630/models/_create_revoke_client_certificate_response_body.py
alibabacloud_cas20200630/models/_create_root_cacertificate_request.py
alibabacloud_cas20200630/models/_create_root_cacertificate_response.py
alibabacloud_cas20200630/models/_create_root_cacertificate_response_body.py
alibabacloud_cas20200630/models/_create_server_certificate_request.py
alibabacloud_cas20200630/models/_create_server_certificate_response.py
alibabacloud_cas20200630/models/_create_server_certificate_response_body.py
alibabacloud_cas20200630-2.0.0.dist-info/LICENSE
alibabacloud_cas20200630-2.0.0.dist-info/METADATA
alibabacloud_cas20200630-2.0.0.dist-info/WHEEL
alibabacloud_cas20200630-2.0.0.dist-info/top_level.txt
alibabacloud_cas20200630-2.0.0.dist-info/RECORD
